uricache/__init__.py
uricache/uricache.py
uricache-0.0.1.dist-info/AUTHORS.rst
uricache-0.0.1.dist-info/LICENSE
uricache-0.0.1.dist-info/METADATA
uricache-0.0.1.dist-info/WHEEL
uricache-0.0.1.dist-info/top_level.txt
uricache-0.0.1.dist-info/RECORD
