Metadata-Version: 2.1
Name: uricache
Version: 0.0.1
Summary: URICache is a caching module that stores data in JSON format, using URI's for accessing the cache.
Home-page: https://github.com/unodan/uricache
Author: Dan Huckson
Author-email: danhuckson@hotmail.com
License: MIT license
Keywords: uricache
Platform: UNKNOWN
Classifier: Development Status :: 2 - Pre-Alpha
Classifier: Intended Audience :: Developers
Classifier: License :: OSI Approved :: MIT License
Classifier: Natural Language :: English
Classifier: Programming Language :: Python :: 2
Classifier: Programming Language :: Python :: 2.7
Classifier: Programming Language :: Python :: 3
Classifier: Programming Language :: Python :: 3.4
Classifier: Programming Language :: Python :: 3.5
Classifier: Programming Language :: Python :: 3.6
Classifier: Programming Language :: Python :: 3.7
